LICENSE
MANIFEST.in
README.rst
setup.py
django_fail.egg-info/PKG-INFO
django_fail.egg-info/SOURCES.txt
django_fail.egg-info/dependency_links.txt
django_fail.egg-info/not-zip-safe
django_fail.egg-info/top_level.txt
fail/__init__.py
fail/decorators.py